{"type":"FeatureCollection","features":[{"type":"Feature","id":34,"geometry":{"type":"Point","coordinates":[-1.8671128209999779,51.650942369000063]},"properties":{"OBJECTID":34,"name":"Test Point","description":"Historical Event","imageURL":null,"siteURL":null,"Category":"HistEvent"}}]}